{"op_code": "25-36", "op_label": "Eric Jacobson", "entity_name": "Eric Jacobson", "grower_since": "2025-03-23", "macro_stage": "baseline_gathered", "current_project_year_id": "P3-2025-Y1", "current_micro_stage": "project_submitted", "projects": [{"project_year_id": "P3-2025-Y1", "year_index": 1, "season_span": "S25 -> F25", "micro_stage": "project_submitted", "acres": 2065.6, "credited_t": 2070.8, "credit_status": "requested"}], "acres_submitted": 2065.6, "n_fields": 7, "submitted_at": "2026-07-12", "true_up_year": 2028, "credited_t": 2070.8, "credits_distributed_to_date": null, "credits_distributed_t_to_date": null, "cluster_bboxes": [{"cluster_id": 0, "min_lon": -99.4611980387, "min_lat": 48.602297641050086, "max_lon": -99.44919557129998, "max_lat": 48.61027794195002, "field_count": 1, "acres": 159.7}, {"cluster_id": 1, "min_lon": -99.64877456182303, "min_lat": 48.477986277412406, "max_lon": -99.5770913272511, "max_lat": 48.51783537400634, "field_count": 2, "acres": 800.8}, {"cluster_id": 2, "min_lon": -99.71138182297214, "min_lat": 48.44313116436998, "max_lon": -99.69944878504785, "max_lat": 48.45109827960344, "field_count": 1, "acres": 158.4}, {"cluster_id": 3, "min_lon": -99.47207715554998, "min_lat": 48.52991095735, "max_lon": -99.46006232745, "max_lat": 48.53788704965011, "field_count": 1, "acres": 160.2}, {"cluster_id": 4, "min_lon": -100.07636134119663, "min_lat": 48.31081639253017, "max_lon": -100.04049517539688, "max_lat": 48.32690942033951, "field_count": 2, "acres": 786.4}], "op_bounds": {"min_lon": -100.074731060933, "min_lat": 48.311547893794234, "max_lon": -99.44974113799998, "max_lat": 48.60991520100002}, "demo_fabricated_status": true}